edzip/__init__.py
edzip/sqlite.py
edzip-0.2.2.dist-info/LICENSE
edzip-0.2.2.dist-info/METADATA
edzip-0.2.2.dist-info/WHEEL
edzip-0.2.2.dist-info/entry_points.txt
edzip-0.2.2.dist-info/RECORD
